search_pr/__init__.py
search_pr/search_pr.py
search_pr-1.0.2.dist-info/LICENSE
search_pr-1.0.2.dist-info/METADATA
search_pr-1.0.2.dist-info/WHEEL
search_pr-1.0.2.dist-info/entry_points.txt
search_pr-1.0.2.dist-info/RECORD
